explorateur/__init__.py
explorateur/_version.py
explorateur/explorateur.py
explorateur/utils.py
explorateur/search/__init__.py
explorateur/search/exploration_type.py
explorateur/search/search_type.py
explorateur/search/storage.py
explorateur/search/transition.py
explorateur/state/__init__.py
explorateur/state/base_move.py
explorateur/state/base_state.py
explorateur/state/storage/__init__.py
explorateur/state/storage/base_storage.py
explorateur/state/storage/factory.py
explorateur/state/storage/hash.py
explorateur/state/storage/priority_queue.py
explorateur/state/storage/queue.py
explorateur/state/storage/stack.py
explorateur-1.2.2.dist-info/LICENSE.md
explorateur-1.2.2.dist-info/METADATA
explorateur-1.2.2.dist-info/WHEEL
explorateur-1.2.2.dist-info/top_level.txt
explorateur-1.2.2.dist-info/RECORD
