Metadata-Version: 2.1
Name: explorateur
Version: 1.2.2
Summary: State space search
Home-page: https://github.com/skadio/explorateur
Author: xxx
Project-URL: Documentation, https://xxx
Project-URL: Source, https://xxx
Classifier: License :: OSI Approved :: Apache Software License
Classifier: Programming Language :: Python :: 3.8
Classifier: Operating System :: OS Independent
License-File: LICENSE.md
